gateway_framework/__init__.py
gateway_framework-0.2.dist-info/METADATA
gateway_framework-0.2.dist-info/WHEEL
gateway_framework-0.2.dist-info/top_level.txt
gateway_framework-0.2.dist-info/RECORD
