Metadata-Version: 2.4
Name: gateway_framework
Version: 0.2
Summary: Gateway framework
Dynamic: summary
